simu_net/__init__.py
simu_net/simu_net.py
simu_net-0.0.2.dist-info/METADATA
simu_net-0.0.2.dist-info/RECORD
simu_net-0.0.2.dist-info/WHEEL
simu_net-0.0.2.dist-info/top_level.txt
