Metadata-Version: 2.1
Name: simu-net
Version: 0.0.2
Summary: Simulation library for TotemBionet
Home-page: https://github.com/clement-alexandre/TotemBionet
Author: Alexandre Clement
Author-email: alexandre.clement@etu.unice.fr
License: WTFPL
Keywords: jupyter,computational systems biology
Platform: UNKNOWN
Classifier: Intended Audience :: Science/Research
Classifier: Topic :: Scientific/Engineering :: Bio-Informatics
Classifier: Programming Language :: Python :: 3.6
Classifier: Programming Language :: Python :: 3.7
Provides-Extra: ipython
Requires-Dist: discrete-model
Requires-Dist: matplotlib (>=3.0.0)
Provides-Extra: ipython
Requires-Dist: tabulate; extra == 'ipython'
